<?xml version="1.0" encoding="UTF-8"?>
<metadata xml:lang="es"><Esri><CreaDate>20230619</CreaDate><CreaTime>10265100</CreaTime><ArcGISFormat>1.0</ArcGISFormat><SyncOnce>TRUE</SyncOnce><DataProperties><lineage><Process ToolSource="c:\program files (x86)\arcgis\desktop10.8\ArcToolbox\Toolboxes\Data Management Tools.tbx\CalculateField" Date="20230619" Time="102651">CalculateField cajerosBUnion entidad "Banco Union" VB #</Process><Process ToolSource="c:\program files (x86)\arcgis\desktop10.8\ArcToolbox\Toolboxes\Data Management Tools.tbx\CalculateField" Date="20230619" Time="103155">CalculateField cajerosBUnion nombre name VB "dim name\nif [id]=2 then\nname="ATM Avenida del Ejercito"\nend if"</Process></lineage></DataProperties></Esri></metadata>
